{
    "name": "graphviper v0.0.38 - graphviper Allure Report",
    "stats": {
        "total": 2,
        "passed": 2
    },
    "status": "passed",
    "duration": 12607,
    "createdAt": 1771854513217,
    "plugin": "Awesome",
    "newTests": [],
    "flakyTests": [],
    "retryTests": [],
    "meta": {
        "reportId": "385ab926-8f4a-481f-ab86-3ee45d53f257",
        "singleFile": false,
        "withTestResultsLinks": true
    },
    "pullRequestHref": "",
    "jobHref": "https://github.com/casangi/testviper/actions/runs/22308550185"
}